pyclustkit/__init__.py
pyclustkit/deepwalk_custom/__init__.py
pyclustkit/deepwalk_custom/__main__.py
pyclustkit/deepwalk_custom/core.py
pyclustkit/deepwalk_custom/graph.py
pyclustkit/deepwalk_custom/skipgram.py
pyclustkit/deepwalk_custom/walks.py
pyclustkit/deepwalk_custom/weighted_random_walk.py
pyclustkit/eval/__init__.py
pyclustkit/eval/_cvi_toolbox.py
pyclustkit/eval/cvi.py
pyclustkit/eval/external_cvi.py
pyclustkit/eval/core/__init__.py
pyclustkit/eval/core/_adg_operations.py
pyclustkit/eval/core/_common_processes.py
pyclustkit/eval/core/_shared_processes.py
pyclustkit/eval/core/_utils.py
pyclustkit/eval/index_specifics/FFT.py
pyclustkit/eval/index_specifics/__init__.py
pyclustkit/eval/index_specifics/_cdbw_tests.py
pyclustkit/eval/index_specifics/representatives.py
pyclustkit/eval/index_specifics/s.py
pyclustkit/eval/index_specifics/sd.py
pyclustkit/eval/utils/__init__.py
pyclustkit/metalearning/__init__.py
pyclustkit/metalearning/_mf_config.py
pyclustkit/metalearning/_mf_extractor.py
pyclustkit/metalearning/cad.py
pyclustkit/metalearning/descriptive.py
pyclustkit/metalearning/landmark.py
pyclustkit/metalearning/marcoge_extractor.py
pyclustkit/metalearning/statistics.py
pyclustkit/metalearning/t_squared.py
pyclustkit/metalearning/utils.py
pyclustkit/metalearning/_marcoge_utils/__init__.py
pyclustkit/metalearning/_marcoge_utils/_data_loading.py
pyclustkit/metalearning/_marcoge_utils/_graph_generation.py
pyclustkit/metalearning/_marcoge_utils/graph_classification_model.py
pyclustkit/metalearning/_marcoge_utils/model_execution.py
pyclustkit/metalearning/_marcoge_utils/utils.py
pyclustkit-0.1.0.dist-info/LICENSE
pyclustkit-0.1.0.dist-info/METADATA
pyclustkit-0.1.0.dist-info/WHEEL
pyclustkit-0.1.0.dist-info/entry_points.txt
pyclustkit-0.1.0.dist-info/top_level.txt
pyclustkit-0.1.0.dist-info/RECORD
